chocolatechip/__init__.py
chocolatechip/Benchmark.py
chocolatechip/console.py
chocolatechip-0.1.0.dist-info/entry_points.txt
chocolatechip-0.1.0.dist-info/METADATA
chocolatechip-0.1.0.dist-info/WHEEL
chocolatechip-0.1.0.dist-info/RECORD
